ncompress.libs/libgcc_s-26206cc5.so.1
ncompress.libs/libstdc++-abeb3405.so.6.0.28
ncompress-1.0.1.dist-info/LICENSE
ncompress-1.0.1.dist-info/WHEEL
ncompress-1.0.1.dist-info/top_level.txt
ncompress-1.0.1.dist-info/RECORD
ncompress-1.0.1.dist-info/METADATA
ncompress/__init__.py
ncompress/ncompress_core.cpython-38-s390x-linux-gnu.so
