Metadata-Version: 2.1
Name: ncompress
Version: 1.0.1
Summary: LZW compression and decompression
Home-page: https://github.com/valgur/ncompress
Author: Martin Valgur
Author-email: martin.valgur@gmail.com
License: Unlicense
Keywords: LZW,compression
Classifier: Programming Language :: Python :: 3
Classifier: Operating System :: OS Independent
Classifier: License :: OSI Approved :: The Unlicense (Unlicense)
Requires-Python: >=3.8
License-File: LICENSE
Provides-Extra: tests
Requires-Dist: pytest ; extra == 'tests'
